copilot/__init__.py
copilot/client.py
copilot/jsonrpc.py
copilot/py.typed
copilot/sdk_protocol_version.py
copilot/session.py
copilot/tools.py
copilot/types.py
copilot/generated/__init__.py
copilot/generated/session_events.py
github_copilot_sdk-0.1.20.dist-info/METADATA
github_copilot_sdk-0.1.20.dist-info/WHEEL
github_copilot_sdk-0.1.20.dist-info/top_level.txt
github_copilot_sdk-0.1.20.dist-info/RECORD
