Metadata-Version: 2.4
Name: github-copilot-sdk
Version: 0.1.20
Summary: Python SDK for GitHub Copilot CLI
Author-email: GitHub <opensource@github.com>
License: MIT
Project-URL: Homepage, https://github.com/github/copilot-sdk
Project-URL: Repository, https://github.com/github/copilot-sdk
Classifier: Development Status :: 3 - Alpha
Classifier: Intended Audience :: Developers
Classifier: License :: OSI Approved :: MIT License
Classifier: Programming Language :: Python :: 3
Classifier: Programming Language :: Python :: 3.9
Classifier: Programming Language :: Python :: 3.10
Classifier: Programming Language :: Python :: 3.11
Classifier: Programming Language :: Python :: 3.12
Requires-Python: >=3.8
Requires-Dist: python-dateutil>=2.9.0.post0
Requires-Dist: pydantic>=2.0
Requires-Dist: typing-extensions>=4.0.0
Provides-Extra: dev
Requires-Dist: ruff>=0.1.0; extra == "dev"
Requires-Dist: ty>=0.0.2; extra == "dev"
Requires-Dist: pytest>=7.0.0; extra == "dev"
Requires-Dist: pytest-asyncio>=0.21.0; extra == "dev"
Requires-Dist: typing-extensions>=4.0.0; extra == "dev"
Requires-Dist: httpx>=0.24.0; extra == "dev"
Dynamic: requires-python
